{"YF7uv0Q98jmrMQasUgsM6Q==":"wlogoredwhitecircle-128x128.png","AK0GrN7zGw5wRvDjiIXdEA==":"mbr-1620x1080.jpg","iXGqyp47dIHI1c5KBfJ/oQ==":"mbr-1-1620x1080.jpg","q69MEBB3buuRFr1Zr64MiQ==":"mbr-720x1080.jpg","/LwM3FhmWjyFYYGXvmOXgA==":"mbr-2-1620x1080.jpg","xnIdjGVHhbGKowHOxNJUpg==":"mbr-1607x1080.jpg","aW1VMAeQFOgFTfzZVHdlwA==":"mbr-1920x1080.jpg","0ccGaWDrPZVeu1gIE2NTtg==":"mbr-1-1920x1080.jpg","tnaBnspVVBuUIZRkPGLP5w==":"mbr-2-1920x1080.jpg","3GL0h8oqhnjX1ASppbJiog==":"mbr-3-1920x1080.jpg","fR5uKl9W0uQGcehyfvPQ7w==":"mbr-1617x1080.jpg"}